<?xml version="1.0" encoding="utf-8"?>
<?xml-stylesheet type="text/xsl" href="cancionALopez.xsl"?>
<cafe xmlns:xsi="http://www.w3.org/2001/XMLSchema-instance" xsi:noNamespaceSchemaLocation="cancionALopez.xsd">
	
	<titulo>Bebidas Calientes</titulo>
	<precio>6 euros</precio>
	<ingrediente>
		<linea>1 café espresso</linea>
		<linea>2/3 taza de leche</linea>
		<linea>2 cucharaditas de azúcar</linea>
		<linea>Canela en polvo o en rama</linea>
		
	</ingrediente>

	<titulo>Cappuccino</titulo>
	<precio>5 euros</precio>
	<ingrediente>
		<linea>1 café espresso</linea>
		<linea>50ml de leche</linea>
		<linea>Un poco de canela o cacao en polvor</linea>
	</ingrediente>

	<titulo>Espresso de Caramelo</titulo>
	<precio>7 euros</precio>
	<ingrediente>
		<linea>2 shot de espresso o espresso doble</linea>
		<linea>1 cucharaditas de sirope de caramelo</linea>
		<linea>30 ml de crema batida (opcional)</linea>
	</ingrediente>
</cafe>